on/__init__.py
on/base.py
on/dig.py
on/errors.py
on/trans.py
on/util.py
on-0.0.3.dist-info/LICENSE
on-0.0.3.dist-info/METADATA
on-0.0.3.dist-info/WHEEL
on-0.0.3.dist-info/top_level.txt
on-0.0.3.dist-info/RECORD
