Metadata-Version: 2.1
Name: on
Version: 0.0.3
Summary: Tools to make data access layers
Home-page: https://github.com/i2mint/on
Author: OtoSense
License: mit
Platform: any
